cort_mcp/__init__.py
cort_mcp/recursive_thinking_ai.py
cort_mcp/server.py
iflow_mcp_cort_mcp-0.2.3.dist-info/licenses/LICENSE
iflow_mcp_cort_mcp-0.2.3.dist-info/METADATA
iflow_mcp_cort_mcp-0.2.3.dist-info/WHEEL
iflow_mcp_cort_mcp-0.2.3.dist-info/entry_points.txt
iflow_mcp_cort_mcp-0.2.3.dist-info/top_level.txt
iflow_mcp_cort_mcp-0.2.3.dist-info/RECORD
