Metadata-Version: 2.4
Name: iflow-mcp_cort-mcp
Version: 0.2.3
Summary: Chain-of-Recursive-Thoughts MCP Server
Author-email: KunihiroS <kunihiros@gmail.com>
License: MIT License
Classifier: Programming Language :: Python :: 3.9
Classifier: Programming Language :: Python :: 3.10
Classifier: Programming Language :: Python :: 3.11
Classifier: Programming Language :: Python :: 3.12
Classifier: License :: OSI Approved :: MIT License
Classifier: Operating System :: OS Independent
Requires-Python: >=3.9
License-File: LICENSE
Requires-Dist: requests
Requires-Dist: pyyaml
Requires-Dist: openai
Requires-Dist: fastmcp>=2.0.0
Dynamic: license-file
